twofourseven/__init__.py
twofourseven/twofourseven.py
twofourseven-0.1.11.dist-info/LICENSE
twofourseven-0.1.11.dist-info/METADATA
twofourseven-0.1.11.dist-info/WHEEL
twofourseven-0.1.11.dist-info/top_level.txt
twofourseven-0.1.11.dist-info/RECORD
