Metadata-Version: 2.1
Name: twofourseven
Version: 0.1.11
Summary: Package to scrape 247Sports website for recruiting data
Home-page: https://github.com/Natron0919/twofourseven/
Author: Nathan Reeb
Author-email: Nathan.Reeb94@outlook.com
License: UNKNOWN
Platform: UNKNOWN
Classifier: Programming Language :: Python :: 3
Classifier: License :: OSI Approved :: GNU General Public License v3 (GPLv3)
Requires-Dist: pandas (>=1)
Requires-Dist: requests (>=2)
Requires-Dist: lxml (>=4)
Requires-Dist: numpy (>=1)
